lauztat/__init__.py
lauztat/config.py
lauztat/parameters.py
lauztat/t_roostat.py
lauztat/util.py
lauztat/calculators/__init__.py
lauztat/calculators/asymptotic_calculator.py
lauztat/calculators/calculator.py
lauztat/calculators/frequentist_calculator.py
lauztat/hypotests/__init__.py
lauztat/hypotests/confidence_interval.py
lauztat/hypotests/discovery.py
lauztat/hypotests/hypotest.py
lauztat/hypotests/upperlimit.py
lauztat/probfit_wrappers/__init__.py
lauztat/probfit_wrappers/loss.py
lauztat/probfit_wrappers/minimizer.py
lauztat/probfit_wrappers/params.py
lauztat/probfit_wrappers/pdf.py
lauztat-1.1.2.data/data/README.rst
lauztat-1.1.2.dist-info/LICENSE
lauztat-1.1.2.dist-info/METADATA
lauztat-1.1.2.dist-info/WHEEL
lauztat-1.1.2.dist-info/dependency_links.txt
lauztat-1.1.2.dist-info/top_level.txt
lauztat-1.1.2.dist-info/RECORD
