Metadata-Version: 2.1
Name: lauztat
Version: 1.1.2
Summary: Pure python statistic tools for high energy physics.
Home-page: https://github.com/marinang/lauztat
Author: Matthieu Marinangeli
Author-email: matthieu.marinangeli@epfl.ch
Maintainer: Matthieu Marinangeli
Maintainer-email: matthieu.marinangeli@epfl.ch
License: UNKNOWN
Platform: Any
Classifier: Intended Audience :: Science/Research
Classifier: Operating System :: MacOS
Classifier: Operating System :: POSIX
Classifier: Operating System :: Unix
Classifier: Programming Language :: Python
Classifier: Programming Language :: Python :: 3.6
Classifier: Programming Language :: Python :: 3.7
Classifier: Topic :: Scientific/Engineering :: Physics
Requires-Dist: attrs (>=18.2.0)
Requires-Dist: scipy
Requires-Dist: numpy
Requires-Dist: zfit
Requires-Dist: matplotlib
